<?xml version="1.0" encoding="UTF-8"?>

<analyticsOfStatements>
    <debtor_originator>Novi most da</debtor_originator>
    <purposeOfPayment>Uplata po racunu 1454/2017</purposeOfPayment>
    <creditor_recipient>Sintelon</creditor_recipient>
    <dateOfReceipt>2017-06-01</dateOfReceipt>
    <currencyDate>2017-06-01</currencyDate>
    <debtorAccount>300745485455555519</debtorAccount>
    <referenceNumberAssigments></referenceNumberAssigments>
    <accountCreditor>400198745874743524</accountCreditor>
    <modelApproval>97</modelApproval>
    <referenceNumberCreditor>326987</referenceNumberCreditor>
    <emergency>true</emergency>
    <sum>45287.0</sum>
    <status></status>
    <paymentType>Nalog za prenos</paymentType>
    <paymentCurrency>din</paymentCurrency>
    <place>Kragujevac</place>
</analyticsOfStatements>